{
    "config":{
       "families":[
          {
             "databases":[
                {
                   "chunk_id_key":"chunkId",
                   "columns":{
                      "data":[
                         {
                            "name":"qserv_trans_id",
                            "type":"INT NOT NULL"
                         },
                         {
                            "name":"galaxy_id",
                            "type":"bigint(20)"
                         },
                         {
                            "name":"halo_id",
                            "type":"bigint(20)"
                         },
                         {
                            "name":"coord_ra",
                            "type":"DOUBLE NOT NULL"
                         },
                         {
                            "name":"coord_dec",
                            "type":"FLOAT NOT NULL"
                         },
                         {
                            "name":"chunkId",
                            "type":"int(11) NOT NULL"
                         },
                         {
                            "name":"subChunkId",
                            "type":"int(11) NOT NULL"
                         }
                      ],
                      "position":[
                         {
                            "name":"qserv_trans_id",
                            "type":"INT NOT NULL"
                         },
                         {
                            "name":"galaxy_id",
                            "type":"bigint(20)"
                         },
                         {
                            "name":"halo_id",
                            "type":"bigint(20)"
                         },
                         {
                            "name":"coord_ra",
                            "type":"DOUBLE NOT NULL"
                         },
                         {
                            "name":"coord_dec",
                            "type":"FLOAT NOT NULL"
                         },
                         {
                            "name":"chunkId",
                            "type":"int(11) NOT NULL"
                         },
                         {
                            "name":"subChunkId",
                            "type":"int(11) NOT NULL"
                         }
                      ]
                   },
                   "director_table":"position",
                   "director_table_key":"galaxy_id",
                   "family":"layout_340_3",
                   "is_published":0,
                   "name":"cosmoDC2_v1_1_4_image_overlap",
                   "sub_chunk_id_key":"subChunkId",
                   "tables":[
                      {
                         "is_partitioned":1,
                         "latitude_key":"coord_dec",
                         "longitude_key":"coord_ra",
                         "name":"position"
                      },
                      {
                         "is_partitioned":1,
                         "latitude_key":"",
                         "longitude_key":"",
                         "name":"data"
                      }
                   ]
                }
             ],
             "min_replication_level":1,
             "name":"layout_340_3",
             "num_stripes":340,
             "num_sub_stripes":3,
             "overlap":0.01667
          }
       ],
       "general":[
          {
             "description":"The default buffer size for network communications.",
             "parameter":"NET_BUF_SIZE_BYTES",
             "updatable":1,
             "value":131072
          },
          {
             "description":"The default retry timeout for network communications.",
             "parameter":"NET_RETRY_TIMEOUT_SEC",
             "updatable":1,
             "value":5
          },
          {
             "description":"The number of threads managed by BOOST ASIO.",
             "parameter":"CONTR_NUM_THREADS",
             "updatable":1,
             "value":64
          }
       ],
       "workers":[
          {
             "data_dir":"/qserv/data/mysql",
             "db_host":"localhost",
             "db_port":3306,
             "db_user":"root",
             "exporter_host":"qserv-worker-0.qserv-worker",
             "exporter_port":25003,
             "exporter_tmp_dir":"/qserv/data/export",
             "fs_host":"qserv-worker-0.qserv-worker",
             "fs_port":25001,
             "http_loader_host":"qserv-worker-0.qserv-worker",
             "http_loader_port":25004,
             "http_loader_tmp_dir":"/qserv/data/ingest",
             "is_enabled":1,
             "is_read_only":0,
             "loader_host":"qserv-worker-0.qserv-worker",
             "loader_port":25002,
             "loader_tmp_dir":"/qserv/data/ingest",
             "name":"qserv-worker-0",
             "svc_host":"qserv-worker-0.qserv-worker",
             "svc_port":25000
          },
          {
             "data_dir":"/qserv/data/mysql",
             "db_host":"localhost",
             "db_port":3306,
             "db_user":"root",
             "exporter_host":"qserv-worker-1.qserv-worker",
             "exporter_port":25003,
             "exporter_tmp_dir":"/qserv/data/export",
             "fs_host":"qserv-worker-1.qserv-worker",
             "fs_port":25001,
             "http_loader_host":"qserv-worker-1.qserv-worker",
             "http_loader_port":25004,
             "http_loader_tmp_dir":"/qserv/data/ingest",
             "is_enabled":1,
             "is_read_only":0,
             "loader_host":"qserv-worker-1.qserv-worker",
             "loader_port":25002,
             "loader_tmp_dir":"/qserv/data/ingest",
             "name":"qserv-worker-1",
             "svc_host":"qserv-worker-1.qserv-worker",
             "svc_port":25000
          }
       ]
    },
    "error":"",
    "error_ext":{
 
    },
    "success":1
 }